teapotai/__init__.py
teapotai/teapot_refusal_classifier.joblib
teapotai/teapotai.py
teapotai-2.0.8.dist-info/licenses/LICENSE
tests/__init__.py
tests/test_teapotai.py
teapotai-2.0.8.dist-info/METADATA
teapotai-2.0.8.dist-info/WHEEL
teapotai-2.0.8.dist-info/top_level.txt
teapotai-2.0.8.dist-info/RECORD
