Metadata-Version: 2.4
Name: teapotai
Version: 2.0.8
Summary: Library for Teapot AI
Home-page: https://github.com/zakerytclarke/teapotai_lib/teapotai
Author: Zakery Clarke
Author-email: zakerytclarke@gmail.com
Project-URL: Documentation, https://teapotai.com/docs
Project-URL: Bug Reports, https://github.com/zakerytclarke/teapot/issues
Project-URL: Source Code, https://github.com/zakerytclarke/teapot
Keywords: llm,teapot
Classifier: Development Status :: 5 - Production/Stable
Classifier: Intended Audience :: Developers
Classifier: Topic :: Software Development :: Build Tools
Classifier: Programming Language :: Python :: 3
Classifier: Programming Language :: Python :: 3.6
Classifier: Programming Language :: Python :: 3.7
Classifier: Programming Language :: Python :: 3.8
Classifier: Programming Language :: Python :: 3.9
Classifier: Programming Language :: Python :: 3 :: Only
Classifier: License :: OSI Approved :: MIT License
Classifier: Operating System :: OS Independent
Requires-Python: >=3.6
License-File: LICENSE
Requires-Dist: torch
Requires-Dist: tqdm
Requires-Dist: transformers
Requires-Dist: numpy
Requires-Dist: scikit-learn
Requires-Dist: pydantic
Requires-Dist: regex
Requires-Dist: langsmith
Provides-Extra: dev
Requires-Dist: check-manifest; extra == "dev"
Provides-Extra: test
Requires-Dist: coverage; extra == "test"
Dynamic: author
Dynamic: author-email
Dynamic: classifier
Dynamic: description
Dynamic: description-content-type
Dynamic: home-page
Dynamic: keywords
Dynamic: license-file
Dynamic: project-url
Dynamic: provides-extra
Dynamic: requires-dist
Dynamic: requires-python
Dynamic: summary
